deepnote_vegafusion-2.0.8.dist-info/METADATA
deepnote_vegafusion-2.0.8.dist-info/WHEEL
deepnote_vegafusion-2.0.8.dist-info/licenses/LICENSE
vegafusion/jupyter/js/index.js
vegafusion/jupyter/__init__.py
vegafusion/local_tz.py
vegafusion/py.typed
vegafusion/runtime.py
vegafusion/transformer.py
vegafusion/utils.py
vegafusion/__init__.py
vegafusion/_vegafusion.pyd
deepnote_vegafusion-2.0.8.dist-info/RECORD
